dashai_stable_diffusion_controlnet_canny_model/__init__.py
dashai_stable_diffusion_controlnet_canny_model/stable_diffusion_controlnet_canny_model.py
dashai_stable_diffusion_controlnet_canny_model-0.0.4.dist-info/METADATA
dashai_stable_diffusion_controlnet_canny_model-0.0.4.dist-info/WHEEL
dashai_stable_diffusion_controlnet_canny_model-0.0.4.dist-info/entry_points.txt
dashai_stable_diffusion_controlnet_canny_model-0.0.4.dist-info/RECORD
